soc/addr_decoder.v
/*
 * Address Decoder for Memory-Mapped SoC
 * 
 * This module decodes memory addresses and generates chip select signals
 * for different memory-mapped peripherals. It also multiplexes read data
 * from the selected module back to the CPU.
 * 
 * Address Map:
 * 0x00000000 - 0x00000FFF: Data Memory (4KB)
 * 0x00001000 - 0x00001FFF: GPIO (4KB)
 * 0x00002000 - 0x00002FFF: Factorial Accelerator (4KB)
 * 
 * Chip selects are one-hot active-high signals.
 */

module addr_decoder (
    // Address and control inputs
    input  wire [31:0] addr,
    input  wire        memRead,
    input  wire        memWrite,
    
    // Read data inputs from each module
    input  wire [31:0] rdata_data_mem,
    input  wire [31:0] rdata_gpio,
    input  wire [31:0] rdata_fact,
    
    // Chip select outputs (one-hot, active-high)
    output wire        cs_data_mem,
    output wire        cs_gpio,
    output wire        cs_fact,
    
    // Multiplexed read data output
    output reg  [31:0] rdata_out
);

    // Address range parameters
    localparam ADDR_DATA_MEM_BASE = 32'h00000000;
    localparam ADDR_DATA_MEM_END  = 32'h00000FFF;
    
    localparam ADDR_GPIO_BASE     = 32'h00001000;
    localparam ADDR_GPIO_END      = 32'h00001FFF;
    
    localparam ADDR_FACT_BASE     = 32'h00002000;
    localparam ADDR_FACT_END      = 32'h00002FFF;
    
    // Address range detection wires
    wire in_data_mem_range;
    wire in_gpio_range;
    wire in_fact_range;
    
    // Address range comparisons
    assign in_data_mem_range = (addr >= ADDR_DATA_MEM_BASE) && (addr <= ADDR_DATA_MEM_END);
    assign in_gpio_range     = (addr >= ADDR_GPIO_BASE)     && (addr <= ADDR_GPIO_END);
    assign in_fact_range     = (addr >= ADDR_FACT_BASE)     && (addr <= ADDR_FACT_END);
    
    // Chip select generation (active when in range AND accessing memory)
    // Chip selects are active for both read and write operations
    assign cs_data_mem = in_data_mem_range && (memRead || memWrite);
    assign cs_gpio     = in_gpio_range     && (memRead || memWrite);
    assign cs_fact     = in_fact_range     && (memRead || memWrite);
    
    // Read data multiplexer
    // Select read data from the appropriate module based on address range
    always @(*) begin
        // Default: return zeros if no module selected
        rdata_out = 32'h00000000;
        
        // Priority-based selection (one-hot by design, so priority doesn't matter)
        if (in_data_mem_range) begin
            rdata_out = rdata_data_mem;
        end
        else if (in_gpio_range) begin
            rdata_out = rdata_gpio;
        end
        else if (in_fact_range) begin
            rdata_out = rdata_fact;
        end
        // else: default to zeros for undefined addresses
    end

endmodule

soc_tb/tb_addr_decoder.v
/*
 * Testbench for Address Decoder Module
 * Tests chip select generation and read data multiplexing
 */

module tb_addr_decoder;

    // Testbench signals
    reg [31:0] addr;
    reg        memRead;
    reg        memWrite;
    
    // Read data inputs (simulated from peripherals)
    reg [31:0] rdata_data_mem;
    reg [31:0] rdata_gpio;
    reg [31:0] rdata_fact;
    
    // Chip select outputs
    wire       cs_data_mem;
    wire       cs_gpio;
    wire       cs_fact;
    
    // Multiplexed read data output
    wire [31:0] rdata_out;
    
    // Address ranges for testing
    localparam ADDR_DATA_MEM = 32'h00000100;  // Within data mem range
    localparam ADDR_GPIO     = 32'h00001000;  // Within GPIO range
    localparam ADDR_FACT     = 32'h00002000;  // Within factorial range
    localparam ADDR_INVALID  = 32'h00003000;  // Outside all ranges

    // One-hot verification helpers (declare at module scope)
    integer one_hot_pass;
    reg [31:0] test_addrs [0:3];
    integer i;
    
    // Instantiate address decoder (port names must match your addr_decoder)
    addr_decoder DUT (
        .addr(addr),
        .memRead(memRead),
        .memWrite(memWrite),
        .rdata_data_mem(rdata_data_mem),
        .rdata_gpio(rdata_gpio),
        .rdata_fact(rdata_fact),
        .cs_data_mem(cs_data_mem),
        .cs_gpio(cs_gpio),
        .cs_fact(cs_fact),
        .rdata_out(rdata_out)
    );
    
    // Task to test chip select generation
    task test_chip_select;
        input [31:0] test_addr;
        input [2:0] expected_cs;
        input [8*32:1] range_name; // string workaround
    begin
        addr = test_addr;
        memRead = 1'b1;
        memWrite = 1'b0;
        #10;
        
        $display("Test: %s (addr=0x%08x)", range_name, test_addr);
        $display("  Expected CS: [data_mem=%b, gpio=%b, fact=%b]", expected_cs[2], expected_cs[1], expected_cs[0]);
        $display("  Actual CS:   [data_mem=%b, gpio=%b, fact=%b]", cs_data_mem, cs_gpio, cs_fact);
        
        if ({cs_data_mem, cs_gpio, cs_fact} == expected_cs) begin
            $display("  ✓ PASS: Chip selects correct");
        end else begin
            $display("  ✗ FAIL: Chip selects mismatch!");
        end
        $display("");
    end
    endtask
    
    // Task to test read data multiplexing
    task test_read_mux;
        input [31:0] test_addr;
        input [31:0] expected_data;
        input [8*32:1] range_name; // string workaround
    begin
        addr = test_addr;
        memRead = 1'b1;
        memWrite = 1'b0;
        #10;
        
        $display("Test: Read from %s (addr=0x%08x)", range_name, test_addr);
        $display("  Expected rdata: 0x%08x", expected_data);
        $display("  Actual rdata:   0x%08x", rdata_out);
        
        if (rdata_out == expected_data) begin
            $display("  ✓ PASS: Read data mux correct");
        end else begin
            $display("  ✗ FAIL: Read data mismatch!");
        end
        $display("");
    end
    endtask
    
    // Main test sequence
    initial begin
        $dumpfile("addr_decoder_tb.vcd");
        $dumpvars(0, tb_addr_decoder);
        
        $display("========================================");
        $display("Address Decoder Testbench");
        $display("========================================\n");
        
        // Initialize signals
        addr = 32'h00000000;
        memRead = 1'b0;
        memWrite = 1'b0;
        rdata_data_mem = 32'hDEADBEEF;
        rdata_gpio = 32'h12345678;
        rdata_fact = 32'hABCDEF00;
        
        #20;
        
        // Test 1: Chip select generation for each range
        $display("=== Test 1: Chip Select Generation ===\n");
        
        test_chip_select(ADDR_DATA_MEM, 3'b100, "Data Memory");
        test_chip_select(ADDR_GPIO,     3'b010, "GPIO");
        test_chip_select(ADDR_FACT,     3'b001, "Factorial");
        test_chip_select(ADDR_INVALID,  3'b000, "Invalid Address");
        
        // Test 2: Chip selects inactive when no memRead/memWrite
        $display("=== Test 2: Chip Selects with No Access ===\n");
        addr = ADDR_DATA_MEM;
        memRead = 1'b0;
        memWrite = 1'b0;
        #10;
        
        $display("Test: Data mem address with memRead=0, memWrite=0");
        $display("  Expected CS: [data_mem=0, gpio=0, fact=0]");
        $display("  Actual CS:   [data_mem=%b, gpio=%b, fact=%b]", cs_data_mem, cs_gpio, cs_fact);
        
        if ({cs_data_mem, cs_gpio, cs_fact} == 3'b000) begin
            $display("  ✓ PASS: Chip selects inactive as expected\n");
        end else begin
            $display("  ✗ FAIL: Chip selects should be inactive!\n");
        end
        
        // Test 3: Read data multiplexing
        $display("=== Test 3: Read Data Multiplexing ===\n");
        
        test_read_mux(ADDR_DATA_MEM, 32'hDEADBEEF, "Data Memory");
        test_read_mux(ADDR_GPIO,     32'h12345678, "GPIO");
        test_read_mux(ADDR_FACT,     32'hABCDEF00, "Factorial");
        test_read_mux(ADDR_INVALID,  32'h00000000, "Invalid Address");
        
        // Test 4: Write operations also activate chip selects
        $display("=== Test 4: Chip Selects on Write ===\n");
        
        addr = ADDR_GPIO;
        memRead = 1'b0;
        memWrite = 1'b1;
        #10;
        
        $display("Test: GPIO write operation");
        $display("  Expected CS: [data_mem=0, gpio=1, fact=0]");
        $display("  Actual CS:   [data_mem=%b, gpio=%b, fact=%b]", cs_data_mem, cs_gpio, cs_fact);
        
        if (cs_gpio == 1'b1 && cs_data_mem == 1'b0 && cs_fact == 1'b0) begin
            $display("  ✓ PASS: GPIO chip select active on write\n");
        end else begin
            $display("  ✗ FAIL: Chip select behavior incorrect on write!\n");
        end
        
        // Test 5: One-hot verification (only one CS active at a time)
        $display("=== Test 5: One-Hot Chip Select Verification ===\n");
        
        one_hot_pass = 1;
        test_addrs[0] = ADDR_DATA_MEM;
        test_addrs[1] = ADDR_GPIO;
        test_addrs[2] = ADDR_FACT;
        test_addrs[3] = ADDR_INVALID;
        memRead = 1'b1;
        memWrite = 1'b0;
        for (i = 0; i < 4; i = i + 1) begin
            addr = test_addrs[i];
            #10;
            // Count number of active chip selects
            if ((cs_data_mem + cs_gpio + cs_fact) > 1) begin
                one_hot_pass = 0;
            end
        end
        if (one_hot_pass == 1)
            $display("  ✓ PASS: One-hot property verified (max 1 CS active)\n");
        else
            $display("  ✗ FAIL: One-hot property violated!\n");
        
        $display("========================================");
        $display("Address Decoder Testbench Completed");
        $display("========================================");
        
        $finish;
    end

endmodule

addr_decoder_tb.vcd
$date
	Fri Dec 05 23:44:15 2025
$end
$version
	Icarus Verilog
$end
$timescale
	1s
$end
$scope module tb_addr_decoder $end
$var wire 32 ! rdata_out [31:0] $end
$var wire 1 " cs_gpio $end
$var wire 1 # cs_fact $end
$var wire 1 $ cs_data_mem $end
$var parameter 32 % ADDR_DATA_MEM $end
$var parameter 32 & ADDR_FACT $end
$var parameter 32 ' ADDR_GPIO $end
$var parameter 32 ( ADDR_INVALID $end
$var reg 32 ) addr [31:0] $end
$var reg 1 * memRead $end
$var reg 1 + memWrite $end
$var reg 32 , rdata_data_mem [31:0] $end
$var reg 32 - rdata_fact [31:0] $end
$var reg 32 . rdata_gpio [31:0] $end
$var integer 32 / i [31:0] $end
$var integer 32 0 one_hot_pass [31:0] $end
$scope module DUT $end
$var wire 32 1 addr [31:0] $end
$var wire 1 $ cs_data_mem $end
$var wire 1 # cs_fact $end
$var wire 1 " cs_gpio $end
$var wire 1 2 in_data_mem_range $end
$var wire 1 3 in_fact_range $end
$var wire 1 4 in_gpio_range $end
$var wire 1 * memRead $end
$var wire 1 + memWrite $end
$var wire 32 5 rdata_data_mem [31:0] $end
$var wire 32 6 rdata_fact [31:0] $end
$var wire 32 7 rdata_gpio [31:0] $end
$var parameter 32 8 ADDR_DATA_MEM_BASE $end
$var parameter 32 9 ADDR_DATA_MEM_END $end
$var parameter 32 : ADDR_FACT_BASE $end
$var parameter 32 ; ADDR_FACT_END $end
$var parameter 32 < ADDR_GPIO_BASE $end
$var parameter 32 = ADDR_GPIO_END $end
$var reg 32 > rdata_out [31:0] $end
$upscope $end
$scope task test_chip_select $end
$var reg 3 ? expected_cs [2:0] $end
$var reg 256 @ range_name [256:1] $end
$var reg 32 A test_addr [31:0] $end
$upscope $end
$scope task test_read_mux $end
$var reg 32 B expected_data [31:0] $end
$var reg 256 C range_name [256:1] $end
$var reg 32 D test_addr [31:0] $end
$upscope $end
$upscope $end
$enddefinitions $end
$comment Show the parameter values. $end
$dumpall
b1111111111111 =
b1000000000000 <
b10111111111111 ;
b10000000000000 :
b111111111111 9
b0 8
b11000000000000 (
b1000000000000 '
b10000000000000 &
b100000000 %
$end
#0
$dumpvars
bx D
bx C
bx B
bx A
bx @
bx ?
b11011110101011011011111011101111 >
b10010001101000101011001111000 7
b10101011110011011110111100000000 6
b11011110101011011011111011101111 5
04
03
12
b0 1
bx 0
bx /
b10010001101000101011001111000 .
b10101011110011011110111100000000 -
b11011110101011011011111011101111 ,
0+
0*
b0 )
0$
0#
0"
b11011110101011011011111011101111 !
$end
#20
1$
1*
b100000000 )
b100000000 1
b100010001100001011101000110000100100000010011010110010101101101011011110111001001111001 @
b100 ?
b100000000 A
#30
0$
1"
b10010001101000101011001111000 !
b10010001101000101011001111000 >
02
14
b1000000000000 )
b1000000000000 1
b1000111010100000100100101001111 @
b10 ?
b1000000000000 A
#40
0"
1#
b10101011110011011110111100000000 !
b10101011110011011110111100000000 >
04
13
b10000000000000 )
b10000000000000 1
b10001100110000101100011011101000110111101110010011010010110000101101100 @
b1 ?
b10000000000000 A
#50
0#
b0 !
b0 >
03
b11000000000000 )
b11000000000000 1
b10010010110111001110110011000010110110001101001011001000010000001000001011001000110010001110010011001010111001101110011 @
b0 ?
b11000000000000 A
#60
b11011110101011011011111011101111 !
b11011110101011011011111011101111 >
12
0*
b100000000 )
b100000000 1
#70
1$
1*
b100010001100001011101000110000100100000010011010110010101101101011011110111001001111001 C
b11011110101011011011111011101111 B
b100000000 D
#80
0$
1"
b10010001101000101011001111000 !
b10010001101000101011001111000 >
02
14
b1000000000000 )
b1000000000000 1
b1000111010100000100100101001111 C
b10010001101000101011001111000 B
b1000000000000 D
#90
0"
1#
b10101011110011011110111100000000 !
b10101011110011011110111100000000 >
04
13
b10000000000000 )
b10000000000000 1
b10001100110000101100011011101000110111101110010011010010110000101101100 C
b10101011110011011110111100000000 B
b10000000000000 D
#100
0#
b0 !
b0 >
03
b11000000000000 )
b11000000000000 1
b10010010110111001110110011000010110110001101001011001000010000001000001011001000110010001110010011001010111001101110011 C
b0 B
b11000000000000 D
#110
1"
b10010001101000101011001111000 !
b10010001101000101011001111000 >
14
1+
0*
b1000000000000 )
b1000000000000 1
#120
1$
0"
b11011110101011011011111011101111 !
b11011110101011011011111011101111 >
12
04
b100000000 )
b100000000 1
b0 /
0+
1*
b1 0
#130
0$
1"
b10010001101000101011001111000 !
b10010001101000101011001111000 >
02
14
b1000000000000 )
b1000000000000 1
b1 /
#140
0"
1#
b10101011110011011110111100000000 !
b10101011110011011110111100000000 >
04
13
b10000000000000 )
b10000000000000 1
b10 /
#150
0#
b0 !
b0 >
03
b11000000000000 )
b11000000000000 1
b11 /
#160
b100 /
