soc/fact_accl.v
// Factorial Accelerator Design
module factorial_accelerator #(
    parameter DATA_WIDTH = 32,
    parameter CNT_WIDTH = 4
)(
    input  wire                    clk,
    input  wire                    reset,
    input  wire                    go,
    input  wire [CNT_WIDTH-1:0]    n,
    output reg  [DATA_WIDTH-1:0]   result,
    output reg                     done,
    output reg                     error
);

    // Internal signals
    wire [CNT_WIDTH-1:0]   cnt_out;
    wire [DATA_WIDTH-1:0]  reg_out;
    wire [DATA_WIDTH-1:0]  mul_out;
    wire [DATA_WIDTH-1:0]  mux_1_out;
    wire                   is_n_gt_12;
    wire                   is_n_gt_1;
    
    // State machine states
    localparam IDLE = 2'b00;
    localparam INIT = 2'b01;
    localparam CALC = 2'b10;
    localparam DONE = 2'b11;
    
    reg [1:0] state, next_state;
    
    // Control signals
    reg load_cnt;
    reg en_cnt;
    reg load_reg;
    reg sel_mux_1;    // 0: select 1, 1: select mul_out
    reg sel_mux_2;    // 0: select 0 (error), 1: select reg_out
    // Down Counter (CNT)
    reg [CNT_WIDTH-1:0] counter;
    
    always @(posedge clk or posedge reset) begin
        if (reset)
            counter <= 0;
        else if (load_cnt)
            counter <= n;
        else if (en_cnt && counter > 1)
            counter <= counter - 1;
    end
    
    assign cnt_out = counter;
    
    // Data Register (REG)
    reg [DATA_WIDTH-1:0] product_reg;
    
    always @(posedge clk or posedge reset) begin
        if (reset)
            product_reg <= 0;
        else if (load_reg)
            product_reg <= mux_1_out;
    end
    
    assign reg_out = product_reg;
    
    // Comparators with GT output (CMP)
    assign is_n_gt_12 = (n > 12) ? 1'b1 : 1'b0;
    assign is_n_gt_1 = (cnt_out > 1) ? 1'b1 : 1'b0;
    
    // Combinational Multiplier (MUL)
    assign mul_out = reg_out * cnt_out;
    
    // MUX_1 (selects between 1 and mul_out)
    assign mux_1_out = sel_mux_1 ? mul_out : 32'd1;
    
    // MUX_2 (selects between 0 and reg_out)
    wire [DATA_WIDTH-1:0] mux_2_out;
    assign mux_2_out = sel_mux_2 ? mux_1_out : 32'd0;
    // State machine - sequential logic
    always @(posedge clk or posedge reset) begin
        if (reset)
            state <= IDLE;
        else
            state <= next_state;
    end
    
    // State machine - combinational logic
    always @(*) begin
        // Default values
        next_state = state;
        load_cnt = 1'b0;
        en_cnt = 1'b0;
        load_reg = 1'b0;
        sel_mux_1 = 1'b0;
        sel_mux_2 = 1'b1;
        done = 1'b0;
        error = 1'b0;
        
        case (state)
            IDLE: begin
                if (go) begin
                    if (is_n_gt_12) begin
                        next_state = DONE;
                        error = 1'b1;
                        sel_mux_2 = 1'b0; // Select 0 for error
                        load_reg = 1'b1;  // Update result register
                    end else if (n == 0 || n == 1) begin
                        next_state = DONE;
                        load_reg = 1'b1;
                        sel_mux_1 = 1'b0; // Load 1 into register
                    end else begin
                        next_state = INIT;
                    end
                end
            end
            
            INIT: begin
                load_cnt = 1'b1;  // Load n into counter
                load_reg = 1'b1;  // Load 1 into register
                sel_mux_1 = 1'b0; // Select 1
                next_state = CALC;
            end
            
            CALC: begin
                if (is_n_gt_1) begin
                    load_reg = 1'b1;  // Load new product
                    sel_mux_1 = 1'b1; // Select mul_out
                    en_cnt = 1'b1;    // Decrement counter
                    next_state = CALC; // Stay in CALC
                end else begin
                    next_state = DONE;
                end
            end
            
            DONE: begin
                done = 1'b1;
                if (!go)
                    next_state = IDLE;
            end
        endcase
    end
    
    // Output assignment
    always @(posedge clk or posedge reset) begin
        if (reset)
            result <= 0;
        else if (load_reg)
            result <= mux_2_out;
    end

endmodule

soc/factorial_wrapper.v
/*
 * Factorial Accelerator Memory-Mapped Wrapper (corrected)
 *
 * Memory Map (32-bit aligned):
 * 0x00002000 - FACT_N_ADDR      (R/W): Input value n (4-bit)
 * 0x00002004 - FACT_CTRL_ADDR   (W)  : Control register (bit0 = start)
 * 0x00002008 - FACT_STATUS_ADDR (R)  : Status register (bit0 = done)
 * 0x0000200C - FACT_RESULT_ADDR (R)  : Result register (32-bit factorial)
 *
 * Notes:
 * - The wrapper generates a single-cycle 'go' pulse for the accelerator
 *   when CPU writes FACT_CTRL with bit0 = 1.
 * - Status/result are sampled from the accelerator.
 */

module factorial_wrapper (
    // System interface
    input  wire        clk,
    input  wire        rst,

    // Memory-mapped interface (CPU-independent)
    input  wire [31:0] addr,
    input  wire [31:0] wdata,
    output reg  [31:0] rdata,
    input  wire        memRead,
    input  wire        memWrite
);

    // Memory-mapped register addresses
    localparam FACT_N_ADDR      = 32'h00002000;  // Input n register
    localparam FACT_CTRL_ADDR   = 32'h00002004;  // Control register (start)
    localparam FACT_STATUS_ADDR = 32'h00002008;  // Status register (done)
    localparam FACT_RESULT_ADDR = 32'h0000200C;  // Result register

    // Internal registers
    reg [3:0]  n_reg;         // Input value n (4-bit)
    reg        start_pulse;   // One-cycle start pulse to accelerator (synchronous)
    reg [31:0] result_reg;    // 32-bit result
    reg        status_reg;    // Done status (sampled from accelerator)

    // Accelerator interface wires
    wire        fact_done;
    wire [31:0] fact_result;
    wire [3:0]  fact_n;
    wire        fact_go;

    // Connect n to accelerator input
    assign fact_n = n_reg;
    assign fact_go = start_pulse;

    // Instantiate the factorial accelerator (user-supplied)
    factorial_accelerator factorial_accel (
        .clk(clk),
        .reset(rst),
        .go(fact_go),
        .n(fact_n),
        .result(fact_result),
        .done(fact_done),
        .error()  // unused
    );

    // Write logic: collect CPU writes and generate a synchronous 1-cycle start pulse
    // start_pulse is asserted for exactly one clock when CPU writes CTRL with bit0=1
    always @(posedge clk or posedge rst) begin
        if (rst) begin
            n_reg       <= 4'h0;
            start_pulse <= 1'b0;
        end else begin
            // default clear the pulse; only assert when memWrite to CTRL in same cycle
            start_pulse <= 1'b0;

            if (memWrite) begin
                case (addr)
                    FACT_N_ADDR: begin
                        // store lower 4 bits of wdata
                        n_reg <= wdata[3:0];
                    end

                    FACT_CTRL_ADDR: begin
                        // generate single-cycle start pulse if bit0==1
                        if (wdata[0]) begin
                            start_pulse <= 1'b1;
                        end
                    end

                    default: begin
                        // ignore writes to other addresses
                    end
                endcase
            end
        end
    end

    // Sample accelerator status/result into wrapper registers
    always @(posedge clk or posedge rst) begin
        if (rst) begin
            status_reg <= 1'b0;
            result_reg <= 32'h00000000;
        end else begin
            // Clear status when starting new operation
            if (memWrite && (addr == FACT_CTRL_ADDR) && wdata[0])
                status_reg <= 1'b0;
            // Set status when done (sticky)
            else if (fact_done)
                status_reg <= 1'b1;
            
            if (fact_done) begin
                result_reg <= fact_result;
            end
        end
    end

    // Combinational read-mux
    always @(*) begin
        rdata = 32'h00000000; // default

        if (memRead) begin
            case (addr)
                FACT_N_ADDR:      rdata = {28'b0, n_reg};               // zero-extend n
                FACT_CTRL_ADDR:   rdata = {31'b0, start_pulse};        // start (for debug)
                FACT_STATUS_ADDR: rdata = {31'b0, status_reg};         // done bit
                FACT_RESULT_ADDR: rdata = result_reg;                  // factorial result
                default:          rdata = 32'h00000000;
            endcase
        end
    end

endmodule

soc/gpio.v
module gpio (
    input  wire        clk,
    input  wire        rst,
    input  wire [31:0] addr,
    input  wire [31:0] wdata,
    output reg  [31:0] rdata,
    input  wire        memRead,
    input  wire        memWrite,

    input  wire [31:0] gpio_in_pins,
    output reg  [31:0] gpio_out_pins
);

    localparam GPIO_IN_ADDR  = 32'h00001000;
    localparam GPIO_OUT_ADDR = 32'h00001004;

    reg [31:0] gpio_out_reg;

    always @ (posedge clk or posedge rst) begin
        if (rst) begin
            gpio_out_reg  <= 32'h00000000;
            gpio_out_pins <= 32'h00000000;
        end
        else begin
            if (memWrite) begin
                case (addr)
                    GPIO_OUT_ADDR: begin
                        gpio_out_reg  <= wdata;
                        gpio_out_pins <= wdata;
                    end

                endcase
            end
        end
    end

    always @(*) begin
        if (memRead) begin
            case (addr)
                GPIO_IN_ADDR:  rdata = gpio_in_pins;
                GPIO_OUT_ADDR: rdata = gpio_out_reg;
                default:       rdata = 32'h00000000;
            endcase
        end
        else begin
            rdata = 32'h00000000;
        end
    end

endmodule

memory/dmem.v
module dmem (
    input  wire        clk,
    input  wire        we,
    input  wire [5:0]  a,
    input  wire [31:0] wd,
    output wire [31:0] rd,
    input  wire        rst
);
    reg [31:0] ram [0:63];
    integer n;

    initial begin
        for (n = 0; n < 64; n = n + 1)
            ram[n] = 32'hFFFFFFFF;
    end

    always @ (posedge clk, posedge rst) begin
        if (rst)
            for (n = 0; n < 64; n = n + 1)
                ram[n] = 32'hFFFFFFFF;
        else if (we)
            ram[a] <= wd;
    end
 assign rd = ram[a];
endmodule

soc/addr_decoder.v


module addr_decoder (

    input  wire [31:0] addr,
    input  wire        memRead,
    input  wire        memWrite,

    input  wire [31:0] rdata_data_mem,
    input  wire [31:0] rdata_gpio,
    input  wire [31:0] rdata_fact,

    output wire        cs_data_mem,
    output wire        cs_gpio,
    output wire        cs_fact,

    output reg  [31:0] rdata_out
);

    localparam ADDR_DATA_MEM_BASE = 32'h00000000;
    localparam ADDR_DATA_MEM_END  = 32'h00000FFF;

    localparam ADDR_GPIO_BASE     = 32'h00001000;
    localparam ADDR_GPIO_END      = 32'h00001FFF;

    localparam ADDR_FACT_BASE     = 32'h00002000;
    localparam ADDR_FACT_END      = 32'h00002FFF;

    wire in_data_mem_range;
    wire in_gpio_range;
    wire in_fact_range;

    assign in_data_mem_range = (addr >= ADDR_DATA_MEM_BASE) && (addr <= ADDR_DATA_MEM_END);
    assign in_gpio_range     = (addr >= ADDR_GPIO_BASE)     && (addr <= ADDR_GPIO_END);
    assign in_fact_range     = (addr >= ADDR_FACT_BASE)     && (addr <= ADDR_FACT_END);

    assign cs_data_mem = in_data_mem_range && (memRead || memWrite);
    assign cs_gpio     = in_gpio_range     && (memRead || memWrite);
    assign cs_fact     = in_fact_range     && (memRead || memWrite);

    always @(*) begin

        rdata_out = 32'h00000000;

        if (in_data_mem_range) begin
            rdata_out = rdata_data_mem;
        end
        else if (in_gpio_range) begin
            rdata_out = rdata_gpio;
        end
        else if (in_fact_range) begin
            rdata_out = rdata_fact;
        end

    end

endmodule

soc/soc_top.v
/*
 * SoC Top-Level Module
 * 
 * This module integrates all memory-mapped peripherals and the address decoder,
 * providing a unified memory interface for CPU integration.
 * 
 * The CPU interface is provided as placeholder ports. No CPU is instantiated here.
 * 
 * Integrated Components:
 * - Data Memory (dmem)
 * - GPIO peripheral
 * - Factorial Accelerator wrapper
 * - Address Decoder
 * 
 * Address Map:
 * 0x00000000 - 0x00000FFF: Data Memory
 * 0x00001000 - 0x00001FFF: GPIO
 * 0x00002000 - 0x00002FFF: Factorial Accelerator
 */

module soc_top (
    // System signals
    input  wire        clk,
    input  wire        rst,
    
    // CPU interface (placeholder - no CPU instantiated)
    input  wire [31:0] cpu_addr,
    input  wire [31:0] cpu_wdata,
    input  wire        cpu_memRead,
    input  wire        cpu_memWrite,
    output wire [31:0] cpu_rdata,
    
    // GPIO external interface
    input  wire [31:0] gpio_in_pins,
    output wire [31:0] gpio_out_pins
);

    // ========================================
    // Internal Signals
    // ========================================
    
    // Chip select signals from address decoder
    wire cs_data_mem;
    wire cs_gpio;
    wire cs_fact;
    
    // Read data signals from each peripheral
    wire [31:0] rdata_data_mem;
    wire [31:0] rdata_gpio;
    wire [31:0] rdata_fact;
    
    // Data memory specific signals
    wire [31:0] dmem_addr_word;
    wire [5:0]  dmem_addr_6bit;
    
    // ========================================
    // Address Decoder
    // ========================================
    
    addr_decoder u_addr_decoder (
        .addr           (cpu_addr),
        .memRead        (cpu_memRead),
        .memWrite       (cpu_memWrite),
        .rdata_data_mem (rdata_data_mem),
        .rdata_gpio     (rdata_gpio),
        .rdata_fact     (rdata_fact),
        .cs_data_mem    (cs_data_mem),
        .cs_gpio        (cs_gpio),
        .cs_fact        (cs_fact),
        .rdata_out      (cpu_rdata)
    );
    
    // ========================================
    // Data Memory (dmem)
    // ========================================
    // Note: dmem uses 6-bit word address (64 words = 256 bytes)
    // Extract bits [7:2] for word addressing
    
    assign dmem_addr_6bit = cpu_addr[7:2];
    
    dmem u_data_mem (
        .clk    (clk),
        .rst    (rst),
        .we     (cs_data_mem & cpu_memWrite),
        .a      (dmem_addr_6bit),
        .wd     (cpu_wdata),
        .rd     (rdata_data_mem)
    );
    
    // ========================================
    // GPIO Peripheral
    // ========================================
    
    gpio u_gpio (
        .clk          (clk),
        .rst          (rst),
        .addr         (cpu_addr),
        .wdata        (cpu_wdata),
        .rdata        (rdata_gpio),
        .memRead      (cs_gpio & cpu_memRead),
        .memWrite     (cs_gpio & cpu_memWrite),
        .gpio_in_pins (gpio_in_pins),
        .gpio_out_pins(gpio_out_pins)
    );
    
    // ========================================
    // Factorial Accelerator Wrapper
    // ========================================
    
    factorial_wrapper u_factorial_wrapper (
        .clk      (clk),
        .rst      (rst),
        .addr     (cpu_addr),
        .wdata    (cpu_wdata),
        .rdata    (rdata_fact),
        .memRead  (cs_fact & cpu_memRead),
        .memWrite (cs_fact & cpu_memWrite)
    );

endmodule

soc_tb/tb_soc_top.v


module tb_soc_top;

    reg        clk;
    reg        rst;

    reg [31:0] cpu_addr;
    reg [31:0] cpu_wdata;
    reg        cpu_memRead;
    reg        cpu_memWrite;
    wire [31:0] cpu_rdata;

    reg [31:0] gpio_in_pins;
    wire [31:0] gpio_out_pins;

    reg [31:0] read_data;
    integer i;

    localparam ADDR_DMEM_BASE = 32'h00000000;

    localparam GPIO_IN_ADDR  = 32'h00001000;
    localparam GPIO_OUT_ADDR = 32'h00001004;

    localparam FACT_N_ADDR      = 32'h00002000;
    localparam FACT_CTRL_ADDR   = 32'h00002004;
    localparam FACT_STATUS_ADDR = 32'h00002008;
    localparam FACT_RESULT_ADDR = 32'h0000200C;

    soc_top DUT (
        .clk(clk),
        .rst(rst),
        .cpu_addr(cpu_addr),
        .cpu_wdata(cpu_wdata),
        .cpu_memRead(cpu_memRead),
        .cpu_memWrite(cpu_memWrite),
        .cpu_rdata(cpu_rdata),
        .gpio_in_pins(gpio_in_pins),
        .gpio_out_pins(gpio_out_pins)
    );

    initial begin
        clk = 0;
        forever #5 clk = ~clk;
    end

    task cpu_write(input [31:0] address, input [31:0] data);
    begin
        @(posedge clk);
        cpu_addr = address;
        cpu_wdata = data;
        cpu_memWrite = 1'b1;
        cpu_memRead = 1'b0;
        @(posedge clk);
        cpu_memWrite = 1'b0;
        $display("  WRITE: addr=0x%08x, data=0x%08x", address, data);
    end
    endtask

    task cpu_read(input [31:0] address, output [31:0] data);
    begin
        @(posedge clk);
        cpu_addr = address;
        cpu_memRead = 1'b1;
        cpu_memWrite = 1'b0;
        @(posedge clk);
        data = cpu_rdata;
        cpu_memRead = 1'b0;
        $display("  READ:  addr=0x%08x, data=0x%08x", address, data);
    end
    endtask

    task wait_cycles(input integer cycles);
    begin
        repeat(cycles) @(posedge clk);
    end
    endtask

    initial begin
        $dumpfile("soc_top_tb.vcd");
        $dumpvars(0, tb_soc_top);

        $display("========================================");
        $display("SoC Top-Level Testbench");
        $display("========================================\n");

        cpu_addr = 32'h00000000;
        cpu_wdata = 32'h00000000;
        cpu_memRead = 1'b0;
        cpu_memWrite = 1'b0;
        gpio_in_pins = 32'h0A0B0C0D;

        rst = 1'b1;
        #20;
        rst = 1'b0;
        #20;

        $display("=== Test 1: Data Memory Access ===");
        $display("Writing to data memory...");
        cpu_write(32'h00000000, 32'hDEADBEEF);
        cpu_write(32'h00000004, 32'h12345678);
        cpu_write(32'h00000008, 32'hABCDEF00);

        $display("Reading from data memory...");
        cpu_read(32'h00000000, read_data);
        if (read_data == 32'hDEADBEEF)
            $display("  ✓ PASS: Data memory read/write correct\n");
        else
            $display("  ✗ FAIL: Expected 0xDEADBEEF, got 0x%08x\n", read_data);

        cpu_read(32'h00000004, read_data);
        if (read_data == 32'h12345678)
            $display("  ✓ PASS: Data memory read/write correct\n");
        else
            $display("  ✗ FAIL: Expected 0x12345678, got 0x%08x\n", read_data);

        $display("=== Test 2: GPIO Access ===");

        $display("Reading GPIO_IN (external pins)...");
        cpu_read(GPIO_IN_ADDR, read_data);
        if (read_data == 32'h0A0B0C0D)
            $display("  ✓ PASS: GPIO_IN read correct\n");
        else
            $display("  ✗ FAIL: Expected 0x0A0B0C0D, got 0x%08x\n", read_data);

        $display("Writing to GPIO_OUT...");
        cpu_write(GPIO_OUT_ADDR, 32'hFEEDFACE);
        wait_cycles(2);

        if (gpio_out_pins == 32'hFEEDFACE)
            $display("  ✓ PASS: GPIO_OUT pins updated correctly\n");
        else
            $display("  ✗ FAIL: Expected 0xFEEDFACE, got 0x%08x\n", gpio_out_pins);

        $display("Reading back GPIO_OUT register...");
        cpu_read(GPIO_OUT_ADDR, read_data);
        if (read_data == 32'hFEEDFACE)
            $display("  ✓ PASS: GPIO_OUT readback correct\n");
        else
            $display("  ✗ FAIL: Expected 0xFEEDFACE, got 0x%08x\n", read_data);

        $display("=== Test 3: GPIO_IN Dynamic Update ===");
        gpio_in_pins = 32'h55AA55AA;
        wait_cycles(3);

        cpu_read(GPIO_IN_ADDR, read_data);
        if (read_data == 32'h55AA55AA)
            $display("  ✓ PASS: GPIO_IN dynamic update correct\n");
        else
            $display("  ✗ FAIL: Expected 0x55AA55AA, got 0x%08x\n", read_data);

        $display("=== Test 4: Factorial Accelerator ===");

        $display("Computing 5! (factorial of 5)...");
        cpu_write(FACT_N_ADDR, 32'h00000005);
        cpu_write(FACT_CTRL_ADDR, 32'h00000001);

        $display("Polling for completion...");
        read_data = 32'h00000000;
        i = 0;
        while (read_data[0] == 1'b0 && i < 100) begin
            cpu_read(FACT_STATUS_ADDR, read_data);
            if (read_data[0] == 1'b0) begin
                wait_cycles(1);
            end
            i = i + 1;
        end

        if (read_data[0] == 1'b1) begin
            $display("  ✓ Factorial computation completed");

            cpu_read(FACT_RESULT_ADDR, read_data);
            if (read_data == 32'd120)
                $display("  ✓ PASS: 5! = %0d (correct)\n", read_data);
            else
                $display("  ✗ FAIL: Expected 120, got %0d\n", read_data);
        end else begin
            $display("  ✗ FAIL: Factorial did not complete in time\n");
        end

        $display("Computing 4! (factorial of 4)...");
        cpu_write(FACT_N_ADDR, 32'h00000004);
        cpu_write(FACT_CTRL_ADDR, 32'h00000001);

        read_data = 32'h00000000;
        i = 0;
        while (read_data[0] == 1'b0 && i < 100) begin
            cpu_read(FACT_STATUS_ADDR, read_data);
            if (read_data[0] == 1'b0) begin
                wait_cycles(1);
            end
            i = i + 1;
        end

        if (read_data[0] == 1'b1) begin
            cpu_read(FACT_RESULT_ADDR, read_data);
            if (read_data == 32'd24)
                $display("  ✓ PASS: 4! = %0d (correct)\n", read_data);
            else
                $display("  ✗ FAIL: Expected 24, got %0d\n", read_data);
        end

        $display("=== Test 5: Verify Address Decoder Routing ===");

        $display("Testing different address ranges...");

        cpu_write(32'h00000010, 32'h11111111);
        cpu_write(GPIO_OUT_ADDR, 32'h22222222);
        cpu_write(FACT_N_ADDR, 32'h00000003);

        cpu_read(32'h00000010, read_data);
        $display("  Data mem read: 0x%08x", read_data);

        cpu_read(GPIO_OUT_ADDR, read_data);
        $display("  GPIO read:     0x%08x", read_data);

        cpu_read(FACT_N_ADDR, read_data);
        $display("  Factorial read: 0x%08x", read_data);

        $display("  ✓ PASS: Address routing verified\n");

        $display("=== Test 6: Invalid Address Access ===");
        cpu_read(32'h00005000, read_data);
        if (read_data == 32'h00000000)
            $display("  ✓ PASS: Invalid address returns 0x00000000\n");
        else
            $display("  ✗ FAIL: Expected 0x00000000, got 0x%08x\n", read_data);

        wait_cycles(5);

        $display("========================================");
        $display("SoC Top-Level Testbench Completed");
        $display("All peripherals verified successfully!");
        $display("========================================");

        $finish;
    end

endmodule

soc_top_tb.vcd
$date
	Sun Dec 14 20:21:29 2025
$end
$version
	Icarus Verilog
$end
$timescale
	1s
$end
$scope module tb_soc_top $end
$var wire 32 ! gpio_out_pins [31:0] $end
$var wire 32 " cpu_rdata [31:0] $end
$var parameter 32 # ADDR_DMEM_BASE $end
$var parameter 32 $ FACT_CTRL_ADDR $end
$var parameter 32 % FACT_N_ADDR $end
$var parameter 32 & FACT_RESULT_ADDR $end
$var parameter 32 ' FACT_STATUS_ADDR $end
$var parameter 32 ( GPIO_IN_ADDR $end
$var parameter 32 ) GPIO_OUT_ADDR $end
$var reg 1 * clk $end
$var reg 32 + cpu_addr [31:0] $end
$var reg 1 , cpu_memRead $end
$var reg 1 - cpu_memWrite $end
$var reg 32 . cpu_wdata [31:0] $end
$var reg 32 / gpio_in_pins [31:0] $end
$var reg 32 0 read_data [31:0] $end
$var reg 1 1 rst $end
$var integer 32 2 i [31:0] $end
$scope module DUT $end
$var wire 1 * clk $end
$var wire 32 3 cpu_addr [31:0] $end
$var wire 1 , cpu_memRead $end
$var wire 1 - cpu_memWrite $end
$var wire 32 4 cpu_wdata [31:0] $end
$var wire 32 5 gpio_in_pins [31:0] $end
$var wire 1 1 rst $end
$var wire 32 6 rdata_gpio [31:0] $end
$var wire 32 7 rdata_fact [31:0] $end
$var wire 32 8 rdata_data_mem [31:0] $end
$var wire 32 9 gpio_out_pins [31:0] $end
$var wire 6 : dmem_addr_6bit [5:0] $end
$var wire 1 ; cs_gpio $end
$var wire 1 < cs_fact $end
$var wire 1 = cs_data_mem $end
$var wire 32 > cpu_rdata [31:0] $end
$scope module u_addr_decoder $end
$var wire 32 ? addr [31:0] $end
$var wire 1 = cs_data_mem $end
$var wire 1 < cs_fact $end
$var wire 1 ; cs_gpio $end
$var wire 1 @ in_data_mem_range $end
$var wire 1 A in_fact_range $end
$var wire 1 B in_gpio_range $end
$var wire 1 , memRead $end
$var wire 1 - memWrite $end
$var wire 32 C rdata_gpio [31:0] $end
$var wire 32 D rdata_fact [31:0] $end
$var wire 32 E rdata_data_mem [31:0] $end
$var parameter 32 F ADDR_DATA_MEM_BASE $end
$var parameter 32 G ADDR_DATA_MEM_END $end
$var parameter 32 H ADDR_FACT_BASE $end
$var parameter 32 I ADDR_FACT_END $end
$var parameter 32 J ADDR_GPIO_BASE $end
$var parameter 32 K ADDR_GPIO_END $end
$var reg 32 L rdata_out [31:0] $end
$upscope $end
$scope module u_data_mem $end
$var wire 6 M a [5:0] $end
$var wire 1 * clk $end
$var wire 32 N rd [31:0] $end
$var wire 1 1 rst $end
$var wire 32 O wd [31:0] $end
$var wire 1 P we $end
$var integer 32 Q n [31:0] $end
$upscope $end
$scope module u_factorial_wrapper $end
$var wire 32 R addr [31:0] $end
$var wire 1 * clk $end
$var wire 1 S fact_go $end
$var wire 1 T memRead $end
$var wire 1 U memWrite $end
$var wire 1 1 rst $end
$var wire 32 V wdata [31:0] $end
$var wire 32 W fact_result [31:0] $end
$var wire 4 X fact_n [3:0] $end
$var wire 1 Y fact_done $end
$var parameter 32 Z FACT_CTRL_ADDR $end
$var parameter 32 [ FACT_N_ADDR $end
$var parameter 32 \ FACT_RESULT_ADDR $end
$var parameter 32 ] FACT_STATUS_ADDR $end
$var reg 4 ^ n_reg [3:0] $end
$var reg 32 _ rdata [31:0] $end
$var reg 32 ` result_reg [31:0] $end
$var reg 1 a start_pulse $end
$var reg 1 b status_reg $end
$scope module factorial_accel $end
$var wire 1 * clk $end
$var wire 1 S go $end
$var wire 4 c n [3:0] $end
$var wire 32 d reg_out [31:0] $end
$var wire 1 1 reset $end
$var wire 32 e mux_2_out [31:0] $end
$var wire 32 f mux_1_out [31:0] $end
$var wire 32 g mul_out [31:0] $end
$var wire 1 h is_n_gt_12 $end
$var wire 1 i is_n_gt_1 $end
$var wire 4 j cnt_out [3:0] $end
$var parameter 2 k CALC $end
$var parameter 32 l CNT_WIDTH $end
$var parameter 32 m DATA_WIDTH $end
$var parameter 2 n DONE $end
$var parameter 2 o IDLE $end
$var parameter 2 p INIT $end
$var reg 4 q counter [3:0] $end
$var reg 1 Y done $end
$var reg 1 r en_cnt $end
$var reg 1 s error $end
$var reg 1 t load_cnt $end
$var reg 1 u load_reg $end
$var reg 2 v next_state [1:0] $end
$var reg 32 w product_reg [31:0] $end
$var reg 32 x result [31:0] $end
$var reg 1 y sel_mux_1 $end
$var reg 1 z sel_mux_2 $end
$var reg 2 { state [1:0] $end
$upscope $end
$upscope $end
$scope module u_gpio $end
$var wire 32 | addr [31:0] $end
$var wire 1 * clk $end
$var wire 32 } gpio_in_pins [31:0] $end
$var wire 1 ~ memRead $end
$var wire 1 !" memWrite $end
$var wire 1 1 rst $end
$var wire 32 "" wdata [31:0] $end
$var parameter 32 #" GPIO_IN_ADDR $end
$var parameter 32 $" GPIO_OUT_ADDR $end
$var reg 32 %" gpio_out_pins [31:0] $end
$var reg 32 &" gpio_out_reg [31:0] $end
$var reg 32 '" rdata [31:0] $end
$upscope $end
$upscope $end
$scope task cpu_read $end
$var reg 32 (" address [31:0] $end
$var reg 32 )" data [31:0] $end
$upscope $end
$scope task cpu_write $end
$var reg 32 *" address [31:0] $end
$var reg 32 +" data [31:0] $end
$upscope $end
$scope task wait_cycles $end
$var integer 32 ," cycles [31:0] $end
$upscope $end
$upscope $end
$enddefinitions $end
$comment Show the parameter values. $end
$dumpall
b1000000000100 $"
b1000000000000 #"
b1 p
b0 o
b11 n
b100000 m
b100 l
b10 k
b10000000001000 ]
b10000000001100 \
b10000000000000 [
b10000000000100 Z
b1111111111111 K
b1000000000000 J
b10111111111111 I
b10000000000000 H
b111111111111 G
b0 F
b1000000000100 )
b1000000000000 (
b10000000001000 '
b10000000001100 &
b10000000000000 %
b10000000000100 $
b0 #
$end
#0
$dumpvars
bx ,"
bx +"
bx *"
bx )"
bx ("
b0 '"
b0 &"
b0 %"
b0 ""
0!"
0~
b1010000010110000110000001101 }
b0 |
b0 {
1z
0y
b0 x
b0 w
b0 v
0u
0t
0s
0r
b0 q
b0 j
0i
0h
b0 g
b1 f
b1 e
b0 d
b0 c
0b
0a
b0 `
b0 _
b0 ^
0Y
b0 X
b0 W
b0 V
0U
0T
0S
b0 R
b1000000 Q
0P
b0 O
b11111111111111111111111111111111 N
b0 M
b11111111111111111111111111111111 L
b11111111111111111111111111111111 E
b0 D
b0 C
0B
0A
1@
b0 ?
b11111111111111111111111111111111 >
0=
0<
0;
b0 :
b0 9
b11111111111111111111111111111111 8
b0 7
b0 6
b1010000010110000110000001101 5
b0 4
b0 3
bx 2
11
bx 0
b1010000010110000110000001101 /
b0 .
0-
0,
b0 +
0*
b11111111111111111111111111111111 "
b0 !
$end
#5
b1000000 Q
1*
#10
0*
#15
b1000000 Q
1*
#20
0*
01
#25
1*
#30
0*
#35
1*
#40
0*
b11011110101011011011111011101111 +"
b0 *"
#45
1P
1=
1-
b11011110101011011011111011101111 .
b11011110101011011011111011101111 4
b11011110101011011011111011101111 O
b11011110101011011011111011101111 V
b11011110101011011011111011101111 ""
1*
#50
0*
#55
b11011110101011011011111011101111 "
b11011110101011011011111011101111 >
b11011110101011011011111011101111 L
b11011110101011011011111011101111 8
b11011110101011011011111011101111 E
b11011110101011011011111011101111 N
0=
0P
b10010001101000101011001111000 +"
b100 *"
0-
1*
#60
0*
#65
1P
1=
b11111111111111111111111111111111 "
b11111111111111111111111111111111 >
b11111111111111111111111111111111 L
b11111111111111111111111111111111 8
b11111111111111111111111111111111 E
b11111111111111111111111111111111 N
b1 :
b1 M
1-
b10010001101000101011001111000 .
b10010001101000101011001111000 4
b10010001101000101011001111000 O
b10010001101000101011001111000 V
b10010001101000101011001111000 ""
b100 +
b100 3
b100 ?
b100 R
b100 |
1*
#70
0*
#75
b10010001101000101011001111000 "
b10010001101000101011001111000 >
b10010001101000101011001111000 L
b10010001101000101011001111000 8
b10010001101000101011001111000 E
b10010001101000101011001111000 N
0=
0P
b10101011110011011110111100000000 +"
b1000 *"
0-
1*
#80
0*
#85
1P
1=
b11111111111111111111111111111111 "
b11111111111111111111111111111111 >
b11111111111111111111111111111111 L
b11111111111111111111111111111111 8
b11111111111111111111111111111111 E
b11111111111111111111111111111111 N
b10 :
b10 M
1-
b10101011110011011110111100000000 .
b10101011110011011110111100000000 4
b10101011110011011110111100000000 O
b10101011110011011110111100000000 V
b10101011110011011110111100000000 ""
b1000 +
b1000 3
b1000 ?
b1000 R
b1000 |
1*
#90
0*
#95
b10101011110011011110111100000000 "
b10101011110011011110111100000000 >
b10101011110011011110111100000000 L
b10101011110011011110111100000000 8
b10101011110011011110111100000000 E
b10101011110011011110111100000000 N
0=
0P
b0 ("
0-
1*
#100
0*
#105
1=
b11011110101011011011111011101111 "
b11011110101011011011111011101111 >
b11011110101011011011111011101111 L
b11011110101011011011111011101111 8
b11011110101011011011111011101111 E
b11011110101011011011111011101111 N
b0 :
b0 M
1,
b0 +
b0 3
b0 ?
b0 R
b0 |
1*
#110
0*
#115
0=
b100 ("
b11011110101011011011111011101111 0
0,
b11011110101011011011111011101111 )"
1*
#120
0*
#125
1=
b10010001101000101011001111000 "
b10010001101000101011001111000 >
b10010001101000101011001111000 L
b10010001101000101011001111000 8
b10010001101000101011001111000 E
b10010001101000101011001111000 N
b1 :
b1 M
1,
b100 +
b100 3
b100 ?
b100 R
b100 |
1*
#130
0*
#135
0=
b1000000000000 ("
b10010001101000101011001111000 0
0,
b10010001101000101011001111000 )"
1*
#140
0*
#145
b1010000010110000110000001101 6
b1010000010110000110000001101 C
b1010000010110000110000001101 '"
1~
1;
b1010000010110000110000001101 "
b1010000010110000110000001101 >
b1010000010110000110000001101 L
b11011110101011011011111011101111 8
b11011110101011011011111011101111 E
b11011110101011011011111011101111 N
b0 :
b0 M
0@
1B
1,
b1000000000000 +
b1000000000000 3
b1000000000000 ?
b1000000000000 R
b1000000000000 |
1*
#150
0*
#155
b0 "
b0 >
b0 L
b0 6
b0 C
b0 '"
0;
0~
b11111110111011011111101011001110 +"
b1000000000100 *"
b1010000010110000110000001101 0
0,
b1010000010110000110000001101 )"
1*
