soc/gpio.v
module gpio (
    input  wire        clk,
    input  wire        rst,
    input  wire [31:0] addr,
    input  wire [31:0] wdata,
    output reg  [31:0] rdata,
    input  wire        memRead,
    input  wire        memWrite,

    input  wire [31:0] gpio_in_pins,
    output reg  [31:0] gpio_out_pins
);

    localparam GPIO_IN_ADDR  = 32'h00001000;
    localparam GPIO_OUT_ADDR = 32'h00001004;

    reg [31:0] gpio_out_reg;

    always @ (posedge clk or posedge rst) begin
        if (rst) begin
            gpio_out_reg  <= 32'h00000000;
            gpio_out_pins <= 32'h00000000;
        end
        else begin
            if (memWrite) begin
                case (addr)
                    GPIO_OUT_ADDR: begin
                        gpio_out_reg  <= wdata;
                        gpio_out_pins <= wdata;
                    end

                endcase
            end
        end
    end

    always @(*) begin
        if (memRead) begin
            case (addr)
                GPIO_IN_ADDR:  rdata = gpio_in_pins;
                GPIO_OUT_ADDR: rdata = gpio_out_reg;
                default:       rdata = 32'h00000000;
            endcase
        end
        else begin
            rdata = 32'h00000000;
        end
    end

endmodule

soc_tb/tb_gpio.v


module tb_gpio;

    reg        clk;
    reg        rst;
    reg [31:0] addr;
    reg [31:0] wdata;
    wire [31:0] rdata;
    reg        memRead;
    reg        memWrite;

    reg [31:0] gpio_in_pins;
    wire [31:0] gpio_out_pins;

    localparam GPIO_IN_ADDR  = 32'h00001000;
    localparam GPIO_OUT_ADDR = 32'h00001004;

    gpio dut (
        .clk(clk),
        .rst(rst),
        .addr(addr),
        .wdata(wdata),
        .rdata(rdata),
        .memRead(memRead),
        .memWrite(memWrite),
        .gpio_in_pins(gpio_in_pins),
        .gpio_out_pins(gpio_out_pins)
    );

    initial begin
        clk = 0;
        forever #5 clk = ~clk;
    end

    initial begin
        $dumpfile("gpio_tb.vcd");
        $dumpvars(0, tb_gpio);

        $display("========================================");
        $display("Starting GPIO Testbench...");
        $display("========================================");

        clk = 0;
        addr = 0;
        wdata = 0;
        memRead = 0;
        memWrite = 0;
        gpio_in_pins = 32'h12345678;

        #10 rst = 0;
        #10;

        $display("Test 1: Reading GPIO_IN register");
        addr = GPIO_IN_ADDR;
        memRead = 1;
        #10;
        $display("GPIO_IN read: Expected=0x12345678, Actual=0x%08x", rdata);
        memRead = 0;
        #10;

        $display("Test 2: Writing to GPIO_OUT register");
        addr = GPIO_OUT_ADDR;
        wdata = 32'hDEADBEEF;
        memWrite = 1;
        #10;
        memWrite = 0;
        $display("GPIO_OUT write: Expected=0xDEADBEEF, Actual=0x%08x", gpio_out_pins);
        #10;

        $display("Test 3: Reading GPIO_OUT register for verification");
        addr = GPIO_OUT_ADDR;
        memRead = 1;
        #10;
        $display("GPIO_OUT read: Expected=0xDEADBEEF, Actual=0x%08x", rdata);
        memRead = 0;
        #10;

        $display("Test 4: Changing GPIO_IN pins and reading");
        gpio_in_pins = 32'hABCDEF00;
        #20;
        addr = GPIO_IN_ADDR;
        memRead = 1;
        #10;
        $display("GPIO_IN read after change: Expected=0xABCDEF00, Actual=0x%08x", rdata);
        memRead = 0;
        #10;

        $display("Test 5: Attempting to write to GPIO_IN (should be ignored)");
        addr = GPIO_IN_ADDR;
        wdata = 32'hFFFFFFFF;
        memWrite = 1;
        #10;
        memWrite = 0;
        #10;

        memRead = 1;
        #10;
        $display("GPIO_IN after write attempt: Expected=0xABCDEF00, Actual=0x%08x", rdata);
        memRead = 0;

        #20;
        $display("========================================");
        $display("GPIO testbench completed successfully!");
        $display("========================================");
        $finish;
    end

endmodule

sim_workspace/gpio_tb.vcd
$date
	Fri Dec 05 23:40:17 2025
$end
$version
	Icarus Verilog
$end
$timescale
	1s
$end
$scope module tb_gpio $end
$var wire 32 ! rdata [31:0] $end
$var wire 32 " gpio_out_pins [31:0] $end
$var parameter 32 # GPIO_IN_ADDR $end
$var parameter 32 $ GPIO_OUT_ADDR $end
$var reg 32 % addr [31:0] $end
$var reg 1 & clk $end
$var reg 32 ' gpio_in_pins [31:0] $end
$var reg 1 ( memRead $end
$var reg 1 ) memWrite $end
$var reg 1 * rst $end
$var reg 32 + wdata [31:0] $end
$scope module dut $end
$var wire 32 , addr [31:0] $end
$var wire 1 & clk $end
$var wire 32 - gpio_in_pins [31:0] $end
$var wire 1 ( memRead $end
$var wire 1 ) memWrite $end
$var wire 1 * rst $end
$var wire 32 . wdata [31:0] $end
$var parameter 32 / GPIO_IN_ADDR $end
$var parameter 32 0 GPIO_OUT_ADDR $end
$var reg 32 1 gpio_out_pins [31:0] $end
$var reg 32 2 gpio_out_reg [31:0] $end
$var reg 32 3 rdata [31:0] $end
$upscope $end
$upscope $end
$enddefinitions $end
$comment Show the parameter values. $end
$dumpall
b1000000000100 0
b1000000000000 /
b1000000000100 $
b1000000000000 #
$end
#0
$dumpvars
b0 3
bx 2
bx 1
b0 .
b10010001101000101011001111000 -
b0 ,
b0 +
x*
0)
0(
b10010001101000101011001111000 '
0&
b0 %
bx "
b0 !
$end
#5
1&
#10
0&
0*
#15
1&
#20
b10010001101000101011001111000 !
b10010001101000101011001111000 3
0&
1(
b1000000000000 %
b1000000000000 ,
#25
1&
#30
b0 !
b0 3
0&
0(
#35
1&
#40
0&
1)
b11011110101011011011111011101111 +
b11011110101011011011111011101111 .
b1000000000100 %
b1000000000100 ,
#45
b11011110101011011011111011101111 "
b11011110101011011011111011101111 1
b11011110101011011011111011101111 2
1&
#50
0&
0)
#55
1&
#60
b11011110101011011011111011101111 !
b11011110101011011011111011101111 3
0&
1(
#65
1&
#70
b0 !
b0 3
0&
0(
#75
1&
#80
0&
b10101011110011011110111100000000 '
b10101011110011011110111100000000 -
#85
1&
#90
0&
#95
1&
#100
b10101011110011011110111100000000 !
b10101011110011011110111100000000 3
0&
1(
b1000000000000 %
b1000000000000 ,
#105
1&
#110
b0 !
b0 3
0&
0(
#115
1&
#120
0&
1)
b11111111111111111111111111111111 +
b11111111111111111111111111111111 .
#125
1&
#130
0&
0)
#135
1&
#140
b10101011110011011110111100000000 !
b10101011110011011110111100000000 3
0&
1(
#145
1&
#150
b0 !
b0 3
0&
0(
